setup.py
xtreme_distributions/Binomialdistribution.py
xtreme_distributions/Gaussiandistribution.py
xtreme_distributions/Generaldistribution.py
xtreme_distributions/__init__.py
xtreme_distributions.egg-info/PKG-INFO
xtreme_distributions.egg-info/SOURCES.txt
xtreme_distributions.egg-info/dependency_links.txt
xtreme_distributions.egg-info/not-zip-safe
xtreme_distributions.egg-info/top_level.txt